config/edrs_asset_stac_mapper.json
config/edrs_search_config.template.yaml
config/edrs_search_config.yaml
config/edrs_session_STAC_template.json
config/edrs_sessions_stac_mapper.json
config/edrs_stations.template.yaml
config/edrs_stations.yaml
rs_server_edrs/__init__.py
rs_server_edrs/api/__init__.py
rs_server_edrs/api/edrs_endpoints.py
rs_server_edrs/edrs_connector.py
rs_server_edrs/edrs_utils.py
rs_server_edrs/fastapi/__init__.py
rs_server_edrs/fastapi/edrs_app.py
rs_server_edrs/fastapi/edrs_routers.py
rs_server_edrs-1.0a6.dist-info/METADATA
rs_server_edrs-1.0a6.dist-info/WHEEL
rs_server_edrs-1.0a6.dist-info/RECORD
